sanic_gunicorn.py
sanic_gunicorn-0.1.2.dist-info/DESCRIPTION.rst
sanic_gunicorn-0.1.2.dist-info/METADATA
sanic_gunicorn-0.1.2.dist-info/RECORD
sanic_gunicorn-0.1.2.dist-info/WHEEL
sanic_gunicorn-0.1.2.dist-info/metadata.json
sanic_gunicorn-0.1.2.dist-info/top_level.txt
