Metadata-Version: 2.0
Name: sanic-gunicorn
Version: 0.1.2
Summary: Gunicorn worker for Sanic
Home-page: https://github.com/messense/sanic-gunicorn
Author: messense
Author-email: messense@icloud.com
License: UNKNOWN
Keywords: sanic,gunicorn
Platform: UNKNOWN
Classifier: Development Status :: 2 - Pre-Alpha
Classifier: Environment :: Web Environment
Classifier: License :: OSI Approved :: MIT License
Classifier: Intended Audience :: Developers
Classifier: Operating System :: MacOS
Classifier: Operating System :: POSIX
Classifier: Operating System :: POSIX :: Linux
Classifier: Programming Language :: Python
Classifier: Programming Language :: Python :: 3.5
Classifier: Programming Language :: Python :: 3.6
Classifier: Programming Language :: Python :: Implementation :: CPython
Classifier: Programming Language :: Python :: Implementation :: PyPy
Requires-Dist: gunicorn
Requires-Dist: sanic (>=0.4.1)
